{
  "posts": [
    {
      "id": 0,
      "userName": "Johnny0",
      "postTitle": "My new car post 0",
      "views": 1949,
      "likes": 14,
      "createdAt": 1437073227668
    },
    {
      "id": 1,
      "userName": "Johnny1",
      "postTitle": "My new car post 1",
      "views": 219,
      "likes": 40,
      "createdAt": 1419949326066
    },
    {
      "id": 2,
      "userName": "Johnny2",
      "postTitle": "My new car post 2",
      "views": 621,
      "likes": 60,
      "createdAt": 1450500030216
    },
    {
      "id": 3,
      "userName": "Johnny3",
      "postTitle": "My new car post 3",
      "views": 202,
      "likes": 15,
      "createdAt": 1464267873061
    },
    {
      "id": 4,
      "userName": "Johnny4",
      "postTitle": "My new car post 4",
      "views": 799,
      "likes": 76,
      "createdAt": 1447615351501
    },
    {
      "id": 5,
      "userName": "Johnny5",
      "postTitle": "My new car post 5",
      "views": 929,
      "likes": 61,
      "createdAt": 1459417055170
    },
    {
      "id": 6,
      "userName": "Johnny6",
      "postTitle": "My new car post 6",
      "views": 1904,
      "likes": 108,
      "createdAt": 1425533738840
    },
    {
      "id": 7,
      "userName": "Johnny7",
      "postTitle": "My new car post 7",
      "views": 1936,
      "likes": 92,
      "createdAt": 1430509421964
    },
    {
      "id": 8,
      "userName": "Johnny8",
      "postTitle": "My new car post 8",
      "views": 855,
      "likes": 148,
      "createdAt": 1422059512787
    },
    {
      "id": 9,
      "userName": "Johnny9",
      "postTitle": "My new car post 9",
      "views": 809,
      "likes": 89,
      "createdAt": 1438450149828
    },
    {
      "id": 10,
      "userName": "Johnny10",
      "postTitle": "My new car post 10",
      "views": 20,
      "likes": 104,
      "createdAt": 1456988563225
    },
    {
      "id": 11,
      "userName": "Johnny11",
      "postTitle": "My new car post 11",
      "views": 1454,
      "likes": 63,
      "createdAt": 1479746737307
    },
    {
      "id": 12,
      "userName": "Johnny12",
      "postTitle": "My new car post 12",
      "views": 1151,
      "likes": 118,
      "createdAt": 1426681361121
    },
    {
      "id": 13,
      "userName": "Johnny13",
      "postTitle": "My new car post 13",
      "views": 1144,
      "likes": 34,
      "createdAt": 1456420281446
    },
    {
      "id": 14,
      "userName": "Johnny14",
      "postTitle": "My new car post 14",
      "views": 297,
      "likes": 89,
      "createdAt": 1441484012699
    },
    {
      "id": 15,
      "userName": "Johnny15",
      "postTitle": "My new car post 15",
      "views": 67,
      "likes": 128,
      "createdAt": 1432263650106
    },
    {
      "id": 16,
      "userName": "Johnny16",
      "postTitle": "My new car post 16",
      "views": 352,
      "likes": 133,
      "createdAt": 1453057272353
    },
    {
      "id": 17,
      "userName": "Johnny17",
      "postTitle": "My new car post 17",
      "views": 374,
      "likes": 14,
      "createdAt": 1419384950413
    },
    {
      "id": 18,
      "userName": "Johnny18",
      "postTitle": "My new car post 18",
      "views": 197,
      "likes": 70,
      "createdAt": 1467848123363
    },
    {
      "id": 19,
      "userName": "Johnny19",
      "postTitle": "My new car post 19",
      "views": 1150,
      "likes": 109,
      "createdAt": 1447726087569
    },
    {
      "id": 20,
      "userName": "Johnny20",
      "postTitle": "My new car post 20",
      "views": 498,
      "likes": 148,
      "createdAt": 1425450814165
    },
    {
      "id": 21,
      "userName": "Johnny21",
      "postTitle": "My new car post 21",
      "views": 468,
      "likes": 99,
      "createdAt": 1456393733806
    },
    {
      "id": 22,
      "userName": "Johnny22",
      "postTitle": "My new car post 22",
      "views": 541,
      "likes": 38,
      "createdAt": 1443792659674
    },
    {
      "id": 23,
      "userName": "Johnny23",
      "postTitle": "My new car post 23",
      "views": 1101,
      "likes": 149,
      "createdAt": 1451052317146
    },
    {
      "id": 24,
      "userName": "Johnny24",
      "postTitle": "My new car post 24",
      "views": 263,
      "likes": 76,
      "createdAt": 1417104481040
    },
    {
      "id": 25,
      "userName": "Johnny25",
      "postTitle": "My new car post 25",
      "views": 517,
      "likes": 103,
      "createdAt": 1471473094095
    },
    {
      "id": 26,
      "userName": "Johnny26",
      "postTitle": "My new car post 26",
      "views": 1479,
      "likes": 150,
      "createdAt": 1423044583908
    },
    {
      "id": 27,
      "userName": "Johnny27",
      "postTitle": "My new car post 27",
      "views": 882,
      "likes": 87,
      "createdAt": 1442247942445
    },
    {
      "id": 28,
      "userName": "Johnny28",
      "postTitle": "My new car post 28",
      "views": 1069,
      "likes": 64,
      "createdAt": 1471822601857
    },
    {
      "id": 29,
      "userName": "Johnny29",
      "postTitle": "My new car post 29",
      "views": 1513,
      "likes": 119,
      "createdAt": 1438224879209
    },
    {
      "id": 30,
      "userName": "Johnny30",
      "postTitle": "My new car post 30",
      "views": 1094,
      "likes": 134,
      "createdAt": 1426619059431
    },
    {
      "id": 31,
      "userName": "Johnny31",
      "postTitle": "My new car post 31",
      "views": 1879,
      "likes": 55,
      "createdAt": 1449529062155
    },
    {
      "id": 32,
      "userName": "Johnny32",
      "postTitle": "My new car post 32",
      "views": 1143,
      "likes": 22,
      "createdAt": 1448757601569
    },
    {
      "id": 33,
      "userName": "Johnny33",
      "postTitle": "My new car post 33",
      "views": 1715,
      "likes": 86,
      "createdAt": 1465650131249
    },
    {
      "id": 34,
      "userName": "Johnny34",
      "postTitle": "My new car post 34",
      "views": 909,
      "likes": 49,
      "createdAt": 1422659906748
    },
    {
      "id": 35,
      "userName": "Johnny35",
      "postTitle": "My new car post 35",
      "views": 1666,
      "likes": 130,
      "createdAt": 1416403506467
    },
    {
      "id": 36,
      "userName": "Johnny36",
      "postTitle": "My new car post 36",
      "views": 1121,
      "likes": 127,
      "createdAt": 1461005394233
    },
    {
      "id": 37,
      "userName": "Johnny37",
      "postTitle": "My new car post 37",
      "views": 1466,
      "likes": 147,
      "createdAt": 1438879893012
    },
    {
      "id": 38,
      "userName": "Johnny38",
      "postTitle": "My new car post 38",
      "views": 720,
      "likes": 53,
      "createdAt": 1460800791098
    },
    {
      "id": 39,
      "userName": "Johnny39",
      "postTitle": "My new car post 39",
      "views": 944,
      "likes": 128,
      "createdAt": 1418680474045
    },
    {
      "id": 40,
      "userName": "Johnny40",
      "postTitle": "My new car post 40",
      "views": 1693,
      "likes": 61,
      "createdAt": 1461107329450
    },
    {
      "id": 41,
      "userName": "Johnny41",
      "postTitle": "My new car post 41",
      "views": 1238,
      "likes": 23,
      "createdAt": 1469308574893
    },
    {
      "id": 42,
      "userName": "Johnny42",
      "postTitle": "My new car post 42",
      "views": 1795,
      "likes": 6,
      "createdAt": 1475478934850
    },
    {
      "id": 43,
      "userName": "Johnny43",
      "postTitle": "My new car post 43",
      "views": 1690,
      "likes": 16,
      "createdAt": 1433612597429
    },
    {
      "id": 44,
      "userName": "Johnny44",
      "postTitle": "My new car post 44",
      "views": 1139,
      "likes": 17,
      "createdAt": 1433126019105
    },
    {
      "id": 45,
      "userName": "Johnny45",
      "postTitle": "My new car post 45",
      "views": 1249,
      "likes": 54,
      "createdAt": 1432290139006
    },
    {
      "id": 46,
      "userName": "Johnny46",
      "postTitle": "My new car post 46",
      "views": 1525,
      "likes": 35,
      "createdAt": 1479714544463
    },
    {
      "id": 47,
      "userName": "Johnny47",
      "postTitle": "My new car post 47",
      "views": 1928,
      "likes": 74,
      "createdAt": 1433773881950
    },
    {
      "id": 48,
      "userName": "Johnny48",
      "postTitle": "My new car post 48",
      "views": 1714,
      "likes": 6,
      "createdAt": 1417383770515
    },
    {
      "id": 49,
      "userName": "Johnny49",
      "postTitle": "My new car post 49",
      "views": 1878,
      "likes": 88,
      "createdAt": 1472485977168
    },
    {
      "id": 50,
      "userName": "Johnny50",
      "postTitle": "My new car post 50",
      "views": 818,
      "likes": 118,
      "createdAt": 1422060681559
    },
    {
      "id": 51,
      "userName": "Johnny51",
      "postTitle": "My new car post 51",
      "views": 1409,
      "likes": 91,
      "createdAt": 1478509710696
    },
    {
      "id": 52,
      "userName": "Johnny52",
      "postTitle": "My new car post 52",
      "views": 517,
      "likes": 12,
      "createdAt": 1461791856798
    },
    {
      "id": 53,
      "userName": "Johnny53",
      "postTitle": "My new car post 53",
      "views": 671,
      "likes": 40,
      "createdAt": 1462569316184
    },
    {
      "id": 54,
      "userName": "Johnny54",
      "postTitle": "My new car post 54",
      "views": 1789,
      "likes": 107,
      "createdAt": 1470819646784
    },
    {
      "id": 55,
      "userName": "Johnny55",
      "postTitle": "My new car post 55",
      "views": 141,
      "likes": 97,
      "createdAt": 1461777958305
    },
    {
      "id": 56,
      "userName": "Johnny56",
      "postTitle": "My new car post 56",
      "views": 1263,
      "likes": 85,
      "createdAt": 1475539091146
    },
    {
      "id": 57,
      "userName": "Johnny57",
      "postTitle": "My new car post 57",
      "views": 371,
      "likes": 69,
      "createdAt": 1417000059418
    },
    {
      "id": 58,
      "userName": "Johnny58",
      "postTitle": "My new car post 58",
      "views": 184,
      "likes": 98,
      "createdAt": 1480115409590
    },
    {
      "id": 59,
      "userName": "Johnny59",
      "postTitle": "My new car post 59",
      "views": 1504,
      "likes": 134,
      "createdAt": 1473324842636
    },
    {
      "id": 60,
      "userName": "Johnny60",
      "postTitle": "My new car post 60",
      "views": 6,
      "likes": 141,
      "createdAt": 1419335612086
    },
    {
      "id": 61,
      "userName": "Johnny61",
      "postTitle": "My new car post 61",
      "views": 1220,
      "likes": 17,
      "createdAt": 1421750753836
    },
    {
      "id": 62,
      "userName": "Johnny62",
      "postTitle": "My new car post 62",
      "views": 146,
      "likes": 5,
      "createdAt": 1419541915162
    },
    {
      "id": 63,
      "userName": "Johnny63",
      "postTitle": "My new car post 63",
      "views": 1164,
      "likes": 19,
      "createdAt": 1429780934645
    },
    {
      "id": 64,
      "userName": "Johnny64",
      "postTitle": "My new car post 64",
      "views": 1180,
      "likes": 126,
      "createdAt": 1456732996519
    },
    {
      "id": 65,
      "userName": "Johnny65",
      "postTitle": "My new car post 65",
      "views": 979,
      "likes": 84,
      "createdAt": 1468729026032
    },
    {
      "id": 66,
      "userName": "Johnny66",
      "postTitle": "My new car post 66",
      "views": 101,
      "likes": 39,
      "createdAt": 1439484982745
    },
    {
      "id": 67,
      "userName": "Johnny67",
      "postTitle": "My new car post 67",
      "views": 1355,
      "likes": 70,
      "createdAt": 1432991064234
    },
    {
      "id": 68,
      "userName": "Johnny68",
      "postTitle": "My new car post 68",
      "views": 578,
      "likes": 18,
      "createdAt": 1468814451916
    },
    {
      "id": 69,
      "userName": "Johnny69",
      "postTitle": "My new car post 69",
      "views": 797,
      "likes": 69,
      "createdAt": 1417222137277
    },
    {
      "id": 70,
      "userName": "Johnny70",
      "postTitle": "My new car post 70",
      "views": 173,
      "likes": 111,
      "createdAt": 1421300634655
    },
    {
      "id": 71,
      "userName": "Johnny71",
      "postTitle": "My new car post 71",
      "views": 822,
      "likes": 75,
      "createdAt": 1418669399325
    },
    {
      "id": 72,
      "userName": "Johnny72",
      "postTitle": "My new car post 72",
      "views": 1806,
      "likes": 130,
      "createdAt": 1448712735555
    },
    {
      "id": 73,
      "userName": "Johnny73",
      "postTitle": "My new car post 73",
      "views": 213,
      "likes": 73,
      "createdAt": 1461008845915
    },
    {
      "id": 74,
      "userName": "Johnny74",
      "postTitle": "My new car post 74",
      "views": 528,
      "likes": 96,
      "createdAt": 1432611475936
    },
    {
      "id": 75,
      "userName": "Johnny75",
      "postTitle": "My new car post 75",
      "views": 1046,
      "likes": 137,
      "createdAt": 1478986861556
    },
    {
      "id": 76,
      "userName": "Johnny76",
      "postTitle": "My new car post 76",
      "views": 1747,
      "likes": 43,
      "createdAt": 1478865055268
    },
    {
      "id": 77,
      "userName": "Johnny77",
      "postTitle": "My new car post 77",
      "views": 701,
      "likes": 69,
      "createdAt": 1457628608128
    },
    {
      "id": 78,
      "userName": "Johnny78",
      "postTitle": "My new car post 78",
      "views": 960,
      "likes": 106,
      "createdAt": 1453369403045
    },
    {
      "id": 79,
      "userName": "Johnny79",
      "postTitle": "My new car post 79",
      "views": 355,
      "likes": 145,
      "createdAt": 1437986113652
    },
    {
      "id": 80,
      "userName": "Johnny80",
      "postTitle": "My new car post 80",
      "views": 886,
      "likes": 87,
      "createdAt": 1417001929875
    },
    {
      "id": 81,
      "userName": "Johnny81",
      "postTitle": "My new car post 81",
      "views": 1826,
      "likes": 119,
      "createdAt": 1473768744592
    },
    {
      "id": 82,
      "userName": "Johnny82",
      "postTitle": "My new car post 82",
      "views": 665,
      "likes": 136,
      "createdAt": 1458190642706
    },
    {
      "id": 83,
      "userName": "Johnny83",
      "postTitle": "My new car post 83",
      "views": 933,
      "likes": 16,
      "createdAt": 1451658109964
    },
    {
      "id": 84,
      "userName": "Johnny84",
      "postTitle": "My new car post 84",
      "views": 1604,
      "likes": 73,
      "createdAt": 1471512488206
    },
    {
      "id": 85,
      "userName": "Johnny85",
      "postTitle": "My new car post 85",
      "views": 306,
      "likes": 39,
      "createdAt": 1419452438837
    },
    {
      "id": 86,
      "userName": "Johnny86",
      "postTitle": "My new car post 86",
      "views": 215,
      "likes": 96,
      "createdAt": 1438324934952
    },
    {
      "id": 87,
      "userName": "Johnny87",
      "postTitle": "My new car post 87",
      "views": 1956,
      "likes": 42,
      "createdAt": 1433361192369
    },
    {
      "id": 88,
      "userName": "Johnny88",
      "postTitle": "My new car post 88",
      "views": 43,
      "likes": 143,
      "createdAt": 1461328120321
    },
    {
      "id": 89,
      "userName": "Johnny89",
      "postTitle": "My new car post 89",
      "views": 1874,
      "likes": 125,
      "createdAt": 1426250139053
    },
    {
      "id": 90,
      "userName": "Johnny90",
      "postTitle": "My new car post 90",
      "views": 1467,
      "likes": 129,
      "createdAt": 1415467365260
    },
    {
      "id": 91,
      "userName": "Johnny91",
      "postTitle": "My new car post 91",
      "views": 1933,
      "likes": 139,
      "createdAt": 1462452737184
    },
    {
      "id": 92,
      "userName": "Johnny92",
      "postTitle": "My new car post 92",
      "views": 1124,
      "likes": 43,
      "createdAt": 1453085401515
    },
    {
      "id": 93,
      "userName": "Johnny93",
      "postTitle": "My new car post 93",
      "views": 965,
      "likes": 110,
      "createdAt": 1440530603031
    },
    {
      "id": 94,
      "userName": "Johnny94",
      "postTitle": "My new car post 94",
      "views": 1383,
      "likes": 84,
      "createdAt": 1459216843963
    },
    {
      "id": 95,
      "userName": "Johnny95",
      "postTitle": "My new car post 95",
      "views": 1141,
      "likes": 109,
      "createdAt": 1431107908635
    },
    {
      "id": 96,
      "userName": "Johnny96",
      "postTitle": "My new car post 96",
      "views": 1150,
      "likes": 105,
      "createdAt": 1447507355992
    },
    {
      "id": 97,
      "userName": "Johnny97",
      "postTitle": "My new car post 97",
      "views": 525,
      "likes": 121,
      "createdAt": 1461467224820
    },
    {
      "id": 98,
      "userName": "Johnny98",
      "postTitle": "My new car post 98",
      "views": 477,
      "likes": 88,
      "createdAt": 1423202865746
    },
    {
      "id": 99,
      "userName": "Johnny99",
      "postTitle": "My new car post 99",
      "views": 401,
      "likes": 54,
      "createdAt": 1476415505875
    },
    {
      "postTitle": "Post 1",
      "views": "1",
      "likes": "1",
      "userName": "Test Johny 1",
      "id": 100
    },
    {
      "postTitle": "Post 2",
      "views": "1",
      "likes": "22",
      "userName": "Test Johny 1",
      "createdAt": 1482244665641,
      "id": 101
    },
    {
      "postTitle": "Test 1",
      "views": "1",
      "likes": "10",
      "userName": "Test Johny 1",
      "createdAt": 1487579690370,
      "id": 102
    },
    {
      "postTitle": "Test post 2",
      "views": 0,
      "likes": 0,
      "userName": "Test Johny 1",
      "createdAt": 1487579756691,
      "id": 103
    },
    {
      "postTitle": "Test post 3",
      "views": 0,
      "likes": 0,
      "userName": "Test Johny 1",
      "createdAt": 1487579915674,
      "id": 104
    },
    {
      "postTitle": "Test post 3",
      "views": 0,
      "likes": 0,
      "userName": "Test Johny 1",
      "createdAt": 1487580006333,
      "id": 105
    },
    {
      "postTitle": "Test post 3",
      "views": 0,
      "likes": 0,
      "userName": "Test Johny 1",
      "createdAt": 1487580006346,
      "id": 106
    },
    {
      "postTitle": "Test post 4",
      "views": 0,
      "likes": 0,
      "userName": "Test Johny 1",
      "createdAt": 1487580075199,
      "id": 107
    },
    {
      "postTitle": "Test post 5",
      "views": 0,
      "likes": 0,
      "userName": "Test Johny 1",
      "createdAt": 1487580440501,
      "id": 108
    },
    {
      "postTitle": "Test post 7",
      "views": 0,
      "likes": 0,
      "userName": "Test Johny 1",
      "createdAt": 1487580569231,
      "id": 109
    },
    {
      "postTitle": "Test post 9",
      "views": 0,
      "likes": 0,
      "userName": "Test Johny 1",
      "createdAt": 1487580657667,
      "id": 110
    },
    {
      "postTitle": "Test post 9",
      "views": 0,
      "likes": 0,
      "userName": "Test Johny 1",
      "createdAt": 1487580712833,
      "id": 111
    },
    {
      "postTitle": "Test post 10",
      "views": 0,
      "likes": 0,
      "userName": "Test Johny 1",
      "createdAt": 1487580979088,
      "id": 112
    },
    {
      "postTitle": "Test post 11",
      "views": 0,
      "likes": 0,
      "userName": "Test Johny 1",
      "createdAt": 1487581031327,
      "id": 113
    },
    {
      "postTitle": "Test 113",
      "views": 0,
      "likes": 0,
      "userName": "Test Johny 1",
      "createdAt": 1487678461571,
      "id": 114
    },
    {
      "postTitle": "Test 114",
      "views": 0,
      "likes": 0,
      "userName": "test@test.com",
      "createdAt": 1487678591845,
      "id": 115
    }
  ]
}